{
  "actions": [
    {
      "id": 1,
      "method": "agent.new",
      "params": {}
    },
    {
      "id": 2,
      "method": "mock.addError",
      "params": {
        "errorType": "transient",
        "message": "provider error"
      }
    },
    {
      "id": 3,
      "method": "agent.run",
      "params": {
        "query": "fail me"
      }
    }
  ],
  "assertions": [
    {
      "id": 1,
      "type": "noError"
    },
    {
      "errorType": "transient",
      "id": 3,
      "type": "error"
    },
    {
      "eventType": "error",
      "type": "event"
    }
  ],
  "description": "Error event published when a query fails",
  "name": "error_event"
}